{
  "collapse-filter": true,
  "search": "-file:.base -#bibliography",
  "showTags": true,
  "showAttachments": false,
  "hideUnresolved": false,
  "showOrphans": true,
  "collapse-color-groups": true,
  "colorGroups": [
    {
      "query": "path:notes/topics/ecs",
      "color": {
        "a": 1,
        "rgb": 14701138
      }
    }
  ],
  "collapse-display": true,
  "showArrow": false,
  "textFadeMultiplier": 0,
  "nodeSizeMultiplier": 1,
  "lineSizeMultiplier": 3,
  "collapse-forces": true,
  "centerStrength": 0.5,
  "repelStrength": 10,
  "linkStrength": 1,
  "linkDistance": 250,
  "scale": 0.3,
  "close": true
}